denobox/__init__.py
denobox/async_box.py
denobox/sync_box.py
denobox/worker.js
denobox-0.1a2.dist-info/licenses/LICENSE
denobox-0.1a2.dist-info/METADATA
denobox-0.1a2.dist-info/WHEEL
denobox-0.1a2.dist-info/top_level.txt
denobox-0.1a2.dist-info/RECORD
