Metadata-Version: 2.4
Name: denobox
Version: 0.1a2
Summary: Execute JavaScript and WebAssembly in a Deno sandbox from Python
Author: Simon Willison
License-Expression: Apache-2.0
Project-URL: Homepage, https://github.com/simonw/denobox
Project-URL: Changelog, https://github.com/simonw/denobox/releases
Project-URL: Issues, https://github.com/simonw/denobox/issues
Project-URL: CI, https://github.com/simonw/denobox/actions
Requires-Python: >=3.10
License-File: LICENSE
Requires-Dist: deno
Dynamic: license-file
